planer_zoo/__init__.py
planer_zoo/test.py
planer_zoo/cellpose/__init__.py
planer_zoo/cellpose/cellpose.py
planer_zoo/cellpose/readme.md
planer_zoo/colorize/__init__.py
planer_zoo/colorize/colorize.py
planer_zoo/colorize/readme.md
planer_zoo/deeplab/__init__.py
planer_zoo/deeplab/deeplab.py
planer_zoo/deeplab/readme.md
planer_zoo/face_68_key/__init__.py
planer_zoo/face_68_key/face_adjust.py
planer_zoo/face_68_key/readme.md
planer_zoo/matting/__init__.py
planer_zoo/matting/fba.md
planer_zoo/matting/fba.py
planer_zoo/matting/human.md
planer_zoo/matting/human.py
planer_zoo/matting/u2net.md
planer_zoo/matting/u2net.py
planer_zoo/obj_recognize/__init__.py
planer_zoo/obj_recognize/readme.md
planer_zoo/obj_recognize/recognize.py
planer_zoo/ocr/__init__.py
planer_zoo/ocr/paddleocr.md
planer_zoo/ocr/paddleocr.py
planer_zoo/old_photos_life/__init__.py
planer_zoo/old_photos_life/readme.md
planer_zoo/old_photos_life/restoration.py
planer_zoo/openpose/__init__.py
planer_zoo/openpose/openpose.py
planer_zoo/openpose/readme.md
planer_zoo/solo/__init__.py
planer_zoo/solo/readme.md
planer_zoo/solo/solov2.py
planer_zoo/super_resolution/__init__.py
planer_zoo/super_resolution/esrgan.py
planer_zoo/super_resolution/readme.md
planer_zoo/vitransformer/__init__.py
planer_zoo/vitransformer/readme.md
planer_zoo/vitransformer/vit.py
planer_zoo/yolo/__init__.py
planer_zoo/yolo/yolov4.md
planer_zoo/yolo/yolov4.py
planer_zoo/yolo/yolov5.md
planer_zoo/yolo/yolov5.py
planer_zoo-0.18.dist-info/LICENSE
planer_zoo-0.18.dist-info/METADATA
planer_zoo-0.18.dist-info/WHEEL
planer_zoo-0.18.dist-info/top_level.txt
planer_zoo-0.18.dist-info/RECORD
