Metadata-Version: 2.1
Name: planer-zoo
Version: 0.18
Summary: toolbox of planer
Home-page: https://github.com/Image-Py/planer-zoo
Author: YXDragon
Author-email: yxdragon@imagepy.org
License: BSD 3-clause
Platform: UNKNOWN
Requires-Dist: planer
Requires-Dist: tqdm
